CHANGES.txt
LICENSE.txt
MANIFEST.in
README.md
TODO.txt
pyproject.toml
setup.cfg
setup.py
tox.ini
src/htmlmeta_hub/__init__.py
src/htmlmeta_hub/py.typed
src/htmlmeta_hub/pyramid_helpers.py
src/htmlmeta_hub.egg-info/PKG-INFO
src/htmlmeta_hub.egg-info/SOURCES.txt
src/htmlmeta_hub.egg-info/dependency_links.txt
src/htmlmeta_hub.egg-info/not-zip-safe
src/htmlmeta_hub.egg-info/requires.txt
src/htmlmeta_hub.egg-info/top_level.txt
tests/__init__.py
tests/test_core.py
tests/test_pyramid_integration.py