Metadata-Version: 2.1
Name: htmlmeta-hub
Version: 0.5.0
Summary: Lightweight support for managing metadata on webpages.
Home-page: https://github.com/jvanasco/htmlmeta_hub
Author: Jonathan Vanasco
Author-email: jonathan@findmeon.com
License: MIT
Keywords: metadata html web pyramid
Classifier: Intended Audience :: Developers
Classifier: Framework :: Pyramid
Classifier: Programming Language :: Python
Classifier: Programming Language :: Python :: 3
Classifier: Programming Language :: Python :: 3.6
Classifier: Programming Language :: Python :: 3.7
Classifier: Programming Language :: Python :: 3.8
Classifier: Programming Language :: Python :: 3.9
Classifier: Programming Language :: Python :: 3.10
Classifier: Programming Language :: Python :: 3.11
Classifier: License :: OSI Approved :: MIT License
Provides-Extra: testing
License-File: LICENSE.txt
